distributors_api/DistributorConnectorBase.py
distributors_api/__init__.py
distributors_api/distributorApiConnector.py
distributors_api/mouser.py
distributors_api/tme.py
distributors_api/tme_base.py
distributors_api-0.1.2a0.dist-info/LICENSE
distributors_api-0.1.2a0.dist-info/METADATA
distributors_api-0.1.2a0.dist-info/WHEEL
distributors_api-0.1.2a0.dist-info/entry_points.txt
distributors_api-0.1.2a0.dist-info/top_level.txt
distributors_api-0.1.2a0.dist-info/RECORD
